setup.py
data_linkage_tool/__init__.py
data_linkage_tool.egg-info/PKG-INFO
data_linkage_tool.egg-info/SOURCES.txt
data_linkage_tool.egg-info/dependency_links.txt
data_linkage_tool.egg-info/not-zip-safe
data_linkage_tool.egg-info/requires.txt
data_linkage_tool.egg-info/top_level.txt