Metadata-Version: 1.0
Name: data-linkage-tool
Version: 0.6
Summary: Do python project
Home-page: https://github.com/thanhtungit92/data_linkage_tool.git
Author: Tung PT
Author-email: thanhtungit92@gmail.com
License: MIT
Platform: UNKNOWN
